parser_2gis/__init__.py
parser_2gis/common.py
parser_2gis/config.py
parser_2gis/exceptions.py
parser_2gis/main.py
parser_2gis/paths.py
parser_2gis/py.typed
parser_2gis/version.py
parser_2gis/chrome/__init__.py
parser_2gis/chrome/browser.py
parser_2gis/chrome/dom.py
parser_2gis/chrome/exceptions.py
parser_2gis/chrome/options.py
parser_2gis/chrome/remote.py
parser_2gis/chrome/utils.py
parser_2gis/chrome/patches/__init__.py
parser_2gis/chrome/patches/pychrome.py
parser_2gis/cli/__init__.py
parser_2gis/cli/app.py
parser_2gis/data/cities.json
parser_2gis/data/rubrics.json
parser_2gis/data/images/icon.icns
parser_2gis/data/images/icon.ico
parser_2gis/data/images/icon.png
parser_2gis/data/images/loading.gif
parser_2gis/data/images/logo.png
parser_2gis/data/images/rubric_folder.png
parser_2gis/data/images/rubric_item.png
parser_2gis/data/images/settings.png
parser_2gis/data/images/settings_inverted.png
parser_2gis/gui/__init__.py
parser_2gis/gui/app.py
parser_2gis/gui/error_popup.py
parser_2gis/gui/rubric_selector.py
parser_2gis/gui/settings.py
parser_2gis/gui/urls_editor.py
parser_2gis/gui/urls_generator.py
parser_2gis/gui/utils.py
parser_2gis/gui/widgets/sg/__init__.py
parser_2gis/gui/widgets/sg/rubrics_tree.py
parser_2gis/gui/widgets/tk/__init__.py
parser_2gis/gui/widgets/tk/custom_entry.py
parser_2gis/gui/widgets/tk/custom_text.py
parser_2gis/gui/widgets/tk/line_numbered_text.py
parser_2gis/logger/__init__.py
parser_2gis/logger/logger.py
parser_2gis/logger/options.py
parser_2gis/parser/__init__.py
parser_2gis/parser/exceptions.py
parser_2gis/parser/factory.py
parser_2gis/parser/options.py
parser_2gis/parser/utils.py
parser_2gis/parser/parsers/__init__.py
parser_2gis/parser/parsers/firm.py
parser_2gis/parser/parsers/in_building.py
parser_2gis/parser/parsers/main.py
parser_2gis/runner/__init__.py
parser_2gis/runner/cli.py
parser_2gis/runner/gui.py
parser_2gis/runner/runner.py
parser_2gis/writer/__init__.py
parser_2gis/writer/exceptions.py
parser_2gis/writer/factory.py
parser_2gis-1.2.1.dist-info/LICENSE
parser_2gis-1.2.1.dist-info/METADATA
parser_2gis-1.2.1.dist-info/WHEEL
parser_2gis-1.2.1.dist-info/entry_points.txt
parser_2gis-1.2.1.dist-info/top_level.txt
parser_2gis-1.2.1.dist-info/RECORD
