Metadata-Version: 2.1
Name: parser-2gis
Version: 1.2.1
Summary: Парсер сайта 2GIS
Home-page: https://github.com/interlark/parser-2gis
Author: Andy Trofimov
Author-email: interlark@gmail.com
License: LGPLv3+
Project-URL: Documentation, https://github.com/interlark/parser-2gis/wiki
Project-URL: GitHub, https://github.com/interlark/parser-2gis
Project-URL: Changelog, https://github.com/interlark/parser-2gis/blob/main/CHANGELOG.md
Keywords: parser scraper 2gis
Classifier: Topic :: Internet
Classifier: Topic :: Utilities
Classifier: Operating System :: OS Independent
Classifier: Programming Language :: Python :: 3 :: Only
Classifier: Programming Language :: Python :: 3.7
Classifier: Programming Language :: Python :: 3.8
Classifier: Programming Language :: Python :: 3.9
Classifier: Programming Language :: Python :: 3.10
Classifier: Natural Language :: Russian
Classifier: Intended Audience :: End Users/Desktop
Classifier: License :: OSI Approved :: GNU Lesser General Public License v3 or later (LGPLv3+)
Requires-Python: >=3.7
Provides-Extra: gui
Provides-Extra: dev
License-File: LICENSE
